fhirkit/AllergyIntolerance.py
fhirkit/BaseModel.py
fhirkit/Bundle.py
fhirkit/CarePlan.py
fhirkit/CareTeam.py
fhirkit/ClinicalImpression.py
fhirkit/CodeSystem.py
fhirkit/Composition.py
fhirkit/CompositionValueSet.py
fhirkit/Condition.py
fhirkit/Coverage.py
fhirkit/Device.py
fhirkit/DiagnosticReport.py
fhirkit/DocumentReference.py
fhirkit/Encounter.py
fhirkit/ImagingStudy.py
fhirkit/Immunization.py
fhirkit/Location.py
fhirkit/Medication.py
fhirkit/MedicationAdministration.py
fhirkit/MedicationRequest.py
fhirkit/MedicationStatement.py
fhirkit/Observation.py
fhirkit/OperationOutcome.py
fhirkit/Organization.py
fhirkit/Parameter.py
fhirkit/Patient.py
fhirkit/Practitioner.py
fhirkit/PractitionerRole.py
fhirkit/Procedure.py
fhirkit/Provenance.py
fhirkit/Resource.py
fhirkit/Server.py
fhirkit/SimpleFHIRStore.py
fhirkit/SupplyDelivery.py
fhirkit/TerminologyServer.py
fhirkit/ValueSet.py
fhirkit/__init__.py
fhirkit/choice_type/__init__.py
fhirkit/choice_type/choice_type.py
fhirkit/choice_type/validators.py
fhirkit/elements/Timing.py
fhirkit/elements/UsageContext.py
fhirkit/elements/__init__.py
fhirkit/elements/elements.py
fhirkit/metadata_types.py
fhirkit/parse.py
fhirkit/primitive_datatypes.py
fhirkit/r5.py
fhirkit/setup.cfg
fhirkit/snomed/ValueSet.py
fhirkit/snomed/__init__.py
fhirkit/snomed/consts.py
fhirkit/snomed/elements.py
fhirkit/snomed/terminology.py
fhirkit/tiro/__init__.py
fhirkit/tiro/elements.py
fhirkit-0.1.0.dist-info/LICENSE.md
fhirkit-0.1.0.dist-info/METADATA
fhirkit-0.1.0.dist-info/WHEEL
fhirkit-0.1.0.dist-info/RECORD
