Metadata-Version: 2.1
Name: fhirkit
Version: 0.1.0
Summary: 
Author: Your Name
Author-email: you@example.com
Requires-Python: >=3.10,<4.0
Classifier: Programming Language :: Python :: 3
Classifier: Programming Language :: Python :: 3.10
Classifier: Programming Language :: Python :: 3.11
Requires-Dist: pydantic (>=1.10,<2.0)
Requires-Dist: pytest
Requires-Dist: pytest-check
Requires-Dist: requests
Requires-Dist: tqdm
